[
  {
    "text": "FURNIZOR: Enel Energie Muntenia SA\n\nFactura piata concurentiala\n\nAdresa: Bulevardul Mircea Voda, nr. 30, et. 5, Camera 5.3, sector\n\n3, Bucuresti, cod postal 030667\n\nCod TVAICIF: RO24387371\n\nNr. ord. reg. com.: J40/14506/2008 PIRLETEANU GEORGE ORIN .\nCap. social subscris si varsat: 37.004.350 lei Intrarea Paltinului, nr. 4, bl. 1, sc. 1, et. 2, ap. 5, localitate\nCont: RO52C1T10000000725076002 OTOPENI, judet Iifov, cod postal 075100\n\nBanca: Citibank Europe plc, Dublin-Sucursala Romania\n\nOperator de date cu caracter personal nr. 10585\n\n&) DETALII NECESARE PLATII eo DATE FACTURA poe COD CLIENT: C103246939\nID FACTURA TOTAL DE PLATA Furnizare energie electrica Adresa domiciliu: Strada MIHAI BRAVU, nr. 177,\n50003962302 74 38 lei Serie si numar: 21MI14074915 localitate OLTENITA, judet Calarasi, cod postal\nCOD PLATA , Data emitere factura: 08.10.2021 915400\n162525431\n\nData scadenta: 25.10.2021\n\nee Tip factura: Estimare\nPerioada de facturare: 01.09.2021 - 30.09.2021\n\nSINTEZA FACTURA\n\n \n\n \n\nTotal de plata factura curenta: 74,38 lei @ MULTUMIM\n\nPlatile sunt efectuate la zi, nu aveti\nfacturi restante.\n\nOQ Componente reglementate 37,72 lei\n\noO Componente negociate 36,66 lei\nCO wwweenel.ro\n0\n\nwww.my.enel.ro\n\nInfo Enel, apel cu tarif\nnormal: 021 9977,\n\nprogram L-V 08:00-20:00, S\nDETALII FISCALE 08:00-13:00\n\n \n\nLg @ CONTACTE UTILE\n\nCc\n\n \n\n \n\n \n\n \n\n \n\nEnergie electrica de facturat 62,01 lei 2 Godetic: woww.enel.ro\n= 7 9 Descopera cel mai\n\nAcciza de facturat 0,49 lei apropiat Magazin Enel pe\n\nTotal baza de impozitare TVA 62,50 lei www.enel.ro\n\nTVA 19% 11,88 lei & Semnalare intreruperi:\n\nTotal de plata factura curenta 74,38 lei o600'07 01888\n\nee I IIIs... yw Adresa de corespondenta:\n\nTotal de plata facturi restante 0,00 lei Bucuresti, Sector 3, bd.\n\nSold total la data emiterii facturii i 74,38 lei Mircea Voda, nr. 30, etaj 5,\ncamera 5.3, cod postal\n030667\n\n© MESAJE a\noe NECLARITATI?\n\nPentru efectuarea si alocarea corecta a platii facturii, foloseste codul de plata si ID-ul acesteia sau doar codul x F mn ,\n\nde plata cand doresti numai plata soldului restant. Daca sunt informa neclare'in\n021 9977* - din 15 aprilie 2020, acesta este noul numar de telefon InfoEnel la care ne poti apela din Romania noua facture, vizital wwwenel.to,\npentru orice informatie comerciala, program L-V 08:00-20:00, S 08:00-13:00; +40372 436 436 - numar apelabil sectiunea ghid nou factura.\n\ndin strainatate.\n\nPentru transmiterea indexului autocitit ramane valabil numarul gratuit 0800070701.\n\n*numar cu tarif normal din orice retea\n\nScanati acest cod daca doriti sa achitati factura curenta in valoare de\n\nHLL\n\n50003962302000000007438081021 16252543159\n\n \n\n \n\n \n\n \n\n \n\n \n\n \n\n \n\n \n\n \n\n \n\n \n\n \n\n \n\n \n\n \n\n \n\n \n\n \n\n \n\n \n\n \n\nPagina 1 din 3 la factura 21M114074915\n",
    "id": 28,
    "label": [
      {
        "start": 178,
        "end": 188,
        "text": "RO24387371",
        "labels": [
          "invoicenumber"
        ]
      },
      {
        "start": 73,
        "end": 163,
        "text": "Bulevardul Mircea Voda, nr. 30, et. 5, Camera 5.3, sector\\n\\n\\n\\n3, Bucuresti, cod postal 030667",
        "labels": [
          "adress"
        ]
      }
    ],
    "annotator": 1,
    "annotation_id": 9,
    "created_at": "2022-04-29T06:38:09.233581Z",
    "updated_at": "2022-04-29T06:38:09.233617Z",
    "lead_time": 22.697
  },
  {
    "text": "   \n\n000043440647\n\n \n\n \n\n‘Ori\n\nDetalii factura fiscala seria MS EON nr. 190009966211 din data de 31.07.2021\n\nCod loc de consum: 5002996638\n4 Denti itt erste HUMENI DANA Numar deranjamente: 0800 800 929/0232 200 A30-\n\n“Adres loc consum: Blvd. 9 MAI, nr. 21, bl. B11,, ap. Ap. 16, PIATRA 2 z\nNEAMT, Judetul Neamt, 610127 Tip pret final:\n\nCod punct de masura: EMO2156637 Serie contor: 25101090\nNivel tensiune punct masura: Perioadad comunicare index autocitit: : 08.08-14.08\n\nNivel tensiune punct delimitare:\n\nee :\n\nCitire regularizare in intervalul:\n\n \n\n \n  \n  \n\nCantitate\nfacturata\n\n \n \n \n \n  \n    \n  \n\n  \n\nfacturare\n\n \n  \n\n11.06.21 -\n13.07.21\n\n11.06.21 -\n13.07.21\n\n11.06.21 -\n13.07.21\n\n11.06.21 -\n30.06.21\n\n11.06.21 -\n\n \n \n\n113,000\n\n \n\n \n    \n \n  \n\n \n \n\nContributie cogenerare factura curenta\n\n \n\n \n\n   \n   \n   \n \n\nCertificate verzi factura curenta\n\n \n\n \n   \n   \n\n \n\n \n\n  \n     \n \n   \n   \n\n \n\nAcciza necomerciala\n\n \n\nTotal energie activa consumata\n\n  \n\nTotal energie activa produsa silivrata in retea\nTotal de plata factura curenta/loc de consum fara TVA [Lei]\nTotal de plata factura curenta/loc de consum cu TVA [Lei]\n\nEnergie activa facturata in perioada similara a anului precedent\n\n \n\n  \n    \n\nTemei legal 2 : Tarife reglementate si acciz [lei/ MWh]\nContribut Ordinul ANRE nr, 239/16.12.2020 ‘Tarif transport: 20,520\"\n\" Legea nr. 220/2008- = ss Tarif distributie: 192,050\nVestimat; -0,4505 CV/MWH - Ordin ANRE 237/2020 2 Tarif servicii de sistem: 10,82\nPret mediu ponderat CV -142,2107 leiiCV z ~_ Accizé scop comercial: 2,61\n\nAcciz’ scop necomercial: 5,23\n\n \n\n \n\n \n",
    "id": 27,
    "label": [
      {
        "start": 72,
        "end": 85,
        "text": "190009966211 ",
        "labels": [
          "invoicenumber"
        ]
      },
      {
        "start": 235,
        "end": 319,
        "text": " Blvd. 9 MAI, nr. 21, bl. B11,, ap. Ap. 16, PIATRA 2 z\\n\\nNEAMT, Judetul Neamt, 610127 ",
        "labels": [
          "adress"
        ]
      }
    ],
    "annotator": 1,
    "annotation_id": 8,
    "created_at": "2022-04-29T06:37:35.037312Z",
    "updated_at": "2022-04-29T06:37:35.037346Z",
    "lead_time": 25.314
  }
]